AverageFU/__init__.py
AFU-1.0.0.dist-info/METADATA
AFU-1.0.0.dist-info/WHEEL
AFU-1.0.0.dist-info/top_level.txt
AFU-1.0.0.dist-info/RECORD
