Metadata-Version: 2.1
Name: AFU
Version: 1.0.0
Summary: average for you
Home-page: UNKNOWN
Author: jerrow4
Author-email: arsninja2000@gmail.com
License: UNKNOWN
Platform: UNKNOWN
Classifier: Programming Language :: Python :: 3
Classifier: License :: OSI Approved :: MIT License
Classifier: Operating System :: OS Independent
Requires-Python: >=3.6
